twix_dl/__init__.py
twix_dl/async_client.py
twix_dl/downloader.py
twix_dl/models.py
twix_dl/sync_client.py
twix_dl/user_agent.py
twix_dl/utils.py
twix_dl/parsers/__init__.py
twix_dl/parsers/parse_error.py
twix_dl/parsers/parse_tweet.py
twix_dl-0.2.0.dist-info/licenses/LICENSE
twix_dl-0.2.0.dist-info/METADATA
twix_dl-0.2.0.dist-info/WHEEL
twix_dl-0.2.0.dist-info/top_level.txt
twix_dl-0.2.0.dist-info/RECORD
