Metadata-Version: 2.4
Name: twix-dl
Version: 0.2.0
Summary: An unofficial X scraper and downloader
Author-email: JellyTyan <jellytyan@jellytyan.de>
License: MIT
Project-URL: Homepage, https://github.com/JellyTyan/twix-dl
Project-URL: Repository, https://github.com/JellyTyan/twix-dl
Project-URL: Bug Tracker, https://github.com/JellyTyan/twix-dl/issues
Project-URL: Documentation, https://github.com/JellyTyan/twix-dl#readme
Keywords: twitter,downloader,media,parser
Classifier: Programming Language :: Python :: 3
Classifier: License :: OSI Approved :: MIT License
Classifier: Operating System :: OS Independent
Requires-Python: >=3.10
License-File: LICENSE
Requires-Dist: httpx>=0.24.0
Dynamic: license-file
